{"Report_Header":{"Created":"2024-02-24","Created_By":"Sheridan PubFactory","Customer_ID":"5923","Report_ID":"PR_P1","Release":"5","Report_Name":"Platform Usage","Institution_Name":"University of Prince Edward Island","Report_Filters":[{"Name":"Access_Method","Value":"Regular"},{"Name":"Metric_Type","Value":"Searches_Platform|Total_Item_Requests|Unique_Item_Requests|Unique_Title_Requests"}],"Exceptions":[{"Code":3020,"Severity":"Error","Message":"Invalid date arguments","Help_URL":null,"Data":"The begin date is missing. The end date is missing."}]},"Report_Items":[]}